dtv2/__init__.py
dtv2/dtv2.py
dtv2/en.json
dtv2/fr.json
dtv2/it.json
dtv2/layouts/__init__.py
dtv2/layouts/en.json
dtv2/layouts/fr.json
dtv2-0.4.8.data/scripts/dtv2change
dtv2-0.4.8.data/scripts/dtv2reader
layouts/__init__.py
dtv2-0.4.8.dist-info/METADATA
dtv2-0.4.8.dist-info/WHEEL
dtv2-0.4.8.dist-info/top_level.txt
dtv2-0.4.8.dist-info/RECORD
