Metadata-Version: 2.1
Name: dtv2
Version: 0.4.8
Summary: Some functions to handle color management on the Drevo Tyrfing V2
Home-page: https://twitter.com/david_cobac
Author: David COBAC
Author-email: david.cobac@gmail.com
License: CC-BY-NC-SA
Keywords: keyboard,drevo,tyrfing
Platform: UNKNOWN
Classifier: Programming Language :: Python :: 3
Classifier: Operating System :: OS Independent
Requires-Dist: hidapi
Requires-Dist: colour
